MANIFEST.in
README.md
setup.cfg
setup.py
agestrucnb.egg-info/PKG-INFO
agestrucnb.egg-info/SOURCES.txt
agestrucnb.egg-info/dependency_links.txt
agestrucnb.egg-info/entry_points.txt
agestrucnb.egg-info/requires.txt
agestrucnb.egg-info/top_level.txt
agestrucne/__init__.py
agestrucne/apgoperation.py
agestrucne/createtooltip.py
agestrucne/genepopfilelociinfo.py
agestrucne/genepopfilemanager.py
agestrucne/genepopfilesampler.py
agestrucne/genepopindividualid.py
agestrucne/indiv.from.perc.and.rep.num.py
agestrucne/negui.py
agestrucne/pgchromlocifilemanager.py
agestrucne/pgdrivelineregress.py
agestrucne/pgdriveneestimator.py
agestrucne/pgdrivesimulation.py
agestrucne/pgframecontainerscrolled.py
agestrucne/pgguiapp.py
agestrucne/pgguineestimator.py
agestrucne/pgguisimupop.py
agestrucne/pgguiutilities.py
agestrucne/pgguiviz.py
agestrucne/pghostnotebook.py
agestrucne/pginputneestimator.py
agestrucne/pginputsimupop.py
agestrucne/pgkeycategoricalvalueframe.py
agestrucne/pgkeycheckboxvalueframe.py
agestrucne/pgkeycontrolframe.py
agestrucne/pgkeylistcomboframe.py
agestrucne/pgkeyvalueframe.py
agestrucne/pgldne2controller.py
agestrucne/pgldne2outputparser.py
agestrucne/pglineregressconfigfilemaker.py
agestrucne/pglisteditingsubframe.py
agestrucne/pgmenubuilder.py
agestrucne/pgneestimationboxplotinterface.py
agestrucne/pgneestimationregressplotinterface.py
agestrucne/pgneestimationtablefilemanager.py
agestrucne/pgneestimationtableselectioncombo.py
agestrucne/pgopneestimator.py
agestrucne/pgopsimupop.py
agestrucne/pgoutputneestimator.py
agestrucne/pgoutputsimupop.py
agestrucne/pgparallelopmanager.py
agestrucne/pgparamset.py
agestrucne/pgplottingframe.py
agestrucne/pgregresser.py
agestrucne/pgregressionstats.py
agestrucne/pgregresstabletextframe.py
agestrucne/pgscalewithentry.py
agestrucne/pgsimupoplociinfo.py
agestrucne/pgsimupopresources.py
agestrucne/pgutilities.py
agestrucne/pgutilityclasses.py
agestrucne/pgvalidationdefs.py
agestrucne/pgvalidationtests.py
agestrucne/setup_negui_environment.py
agestrucne/asnviz/FileIO.py
agestrucne/asnviz/GraphDrive.py
agestrucne/asnviz/LineRegress.py
agestrucne/asnviz/SimBatchRun.py
agestrucne/asnviz/StatsDriver.py
