Metadata-Version: 1.2
Name: agestrucnb
Version: 0.1.33
Summary: GUI and command line program for simulating populations using simuPOP, estimating Nb and Ne using LDNe, and vizualizing the results.
Home-page: UNKNOWN
Author: several people
Author-email: agestrucne@gmail.com
License: AGPLv3
Keywords: population genetics,simuPOP,LDNe,AgeStructureNe
Platform: UNKNOWN
Classifier: License :: OSI Approved :: GNU Affero General Public License v3
Requires-Python: >=2.7, !=3.0.*, !=3.1.*, !=3.2.*, !=3.3.*,<=4
